jupyter_kernel_pathresolver/__init__.py
jupyter_kernel_pathresolver/kernel_manager.py
jupyter_kernel_pathresolver-0.0.1.dist-info/METADATA
jupyter_kernel_pathresolver-0.0.1.dist-info/WHEEL
jupyter_kernel_pathresolver-0.0.1.dist-info/RECORD
