Metadata-Version: 2.4
Name: jupyter-kernel-pathresolver
Version: 0.0.1
Summary: Jupyter kernel manager extension that resolves kernel working directory paths, especially for symlinked and special directories
License: MIT
Classifier: Framework :: Jupyter
Classifier: Programming Language :: Python
Classifier: Programming Language :: Python :: 3.12
Requires-Python: >=3.12
Requires-Dist: jupyter-server==2.16.0
